{"uid":"c82feb92697e33ac","name":"Verify the bad request message display in response when lat/long cordinates missing/invalid","fullName":"com.ginie1_qa.ApiTest.testMissingCordinates","historyId":"f901b6773d4f2070c487d71453d4924b","time":{"start":1737095437329,"stop":1737095438291,"duration":962},"status":"passed","flaky":false,"newFailed":false,"newBroken":false,"newPassed":false,"retriesCount":0,"retriesStatusChange":false,"beforeStages":[{"name":"setUp","time":{"start":1737095427798,"stop":1737095427802,"duration":4},"description":"","status":"passed","steps":[],"attachments":[],"parameters":[],"shouldDisplayMessage":false,"attachmentsCount":0,"attachmentStep":false,"hasContent":false,"stepsCount":0}],"afterStages":[],"labels":[{"name":"package","value":"com.ginie1_qa.ApiTest"},{"name":"testClass","value":"com.ginie1_qa.ApiTest"},{"name":"testMethod","value":"testMissingCordinates"},{"name":"parentSuite","value":"Surefire suite"},{"name":"suite","value":"Surefire test"},{"name":"subSuite","value":"com.ginie1_qa.ApiTest"},{"name":"host","value":"CTNL2272"},{"name":"thread","value":"14348@CTNL2272.main(1)"},{"name":"framework","value":"testng"},{"name":"language","value":"java"},{"name":"resultFormat","value":"allure2"}],"parameters":[],"links":[],"hidden":false,"retry":false,"extra":{"severity":"normal","retries":[],"categories":[],"tags":[]},"source":"c82feb92697e33ac.json","parameterValues":[]}